CHANGELOG
LICENSE
MANIFEST.in
README.md
requirements.txt
setup.py
pyersinia.egg-info/PKG-INFO
pyersinia.egg-info/SOURCES.txt
pyersinia.egg-info/dependency_links.txt
pyersinia.egg-info/entry_points.txt
pyersinia.egg-info/requires.txt
pyersinia.egg-info/top_level.txt
pyersinia_lib/__init__.py
pyersinia_lib/api.py
pyersinia_lib/data.py
pyersinia_lib/pyersinia.py
pyersinia_lib/doc/__init__.py
pyersinia_lib/doc/en/__init__.py
pyersinia_lib/doc/en/source/__init__.py
pyersinia_lib/doc/en/source/conf.py
pyersinia_lib/libs/__init__.py
pyersinia_lib/libs/plugins/__init__.py
pyersinia_lib/libs/plugins/arp_poison.py
pyersinia_lib/libs/plugins/dhcp_discover_dos.py
pyersinia_lib/libs/plugins/stp_bdpu_conf.py
pyersinia_lib/libs/plugins/stp_root_role.py
pyersinia_lib/libs/plugins/stp_tcn.py
pyersinia_lib/libs/plugins/vlan_hooping_trunk.py