Metadata-Version: 1.1
Name: pyersinia
Version: 1.0.5
Summary: Herramienta para ataques de capa de enlace
Home-page: https://github.com/nottinghamprisateam/pyersinia
Author: Nottingham Prisa Team
Author-email: pyersinia94@gmail.com
License: BSD
Platform: UNKNOWN
Classifier: Environment :: Console
Classifier: Intended Audience :: System Administrators
Classifier: Intended Audience :: Other Audience
Classifier: License :: OSI Approved :: BSD License
Classifier: Operating System :: MacOS
Classifier: Operating System :: POSIX
Classifier: Programming Language :: Python :: 2
Classifier: Programming Language :: Python :: 3
Classifier: Topic :: Security
